kisstvshow/__init__.py
kisstvshow/kisstvshow.py
kisstvshow/utils.py
kisstvshow-0.1.0.dist-info/LICENSE
kisstvshow-0.1.0.dist-info/METADATA
kisstvshow-0.1.0.dist-info/WHEEL
kisstvshow-0.1.0.dist-info/RECORD
