Metadata-Version: 2.1
Name: kisstvshow
Version: 0.1.0
Summary: 
Author: tbdsux
Author-email: iamcoderx@gmail.com
Requires-Python: >=3.10,<4.0
Classifier: Programming Language :: Python :: 3
Classifier: Programming Language :: Python :: 3.10
Classifier: Programming Language :: Python :: 3.11
Requires-Dist: bs4 (>=0.0.1,<0.0.2)
Requires-Dist: lxml (>=4.9.2,<5.0.0)
Requires-Dist: requests (>=2.30.0,<3.0.0)
